hanging_threads.py
hanging_threads-2.0.7.dist-info/LICENSE
hanging_threads-2.0.7.dist-info/METADATA
hanging_threads-2.0.7.dist-info/WHEEL
hanging_threads-2.0.7.dist-info/top_level.txt
hanging_threads-2.0.7.dist-info/RECORD
