Metadata-Version: 2.1
Name: hanging-threads
Version: 2.0.7
Summary: Deadlocks? Detect where your threads hang in Python with one import.
Home-page: https://github.com/niccokunzmann/hanging_threads
Author: Nicco Kunzmann
Author-email: niccokunzmann@gmail.com
License: MIT
Platform: any
Classifier: Development Status :: 4 - Beta
Classifier: Intended Audience :: Developers
Classifier: License :: OSI Approved :: MIT License
Classifier: Programming Language :: Python :: 2.6
Classifier: Programming Language :: Python :: 2.7
Classifier: Programming Language :: Python :: 3
Classifier: Programming Language :: Python :: 3.2
Classifier: Programming Language :: Python :: 3.3
Classifier: Programming Language :: Python :: 3.4
Classifier: Programming Language :: Python :: 3.5
Classifier: Programming Language :: Python :: 3.6
License-File: LICENSE
